{
  "db_name": "PostgreSQL",
  "query": "\n                SELECT * FROM users\n                WHERE username = $1\n            ",
  "describe": {
    "columns": [
      {
        "ordinal": 0,
        "name": "id",
        "type_info": "Int4"
      },
      {
        "ordinal": 1,
        "name": "username",
        "type_info": "Varchar"
      },
      {
        "ordinal": 2,
        "name": "avatar",
        "type_info": "Text"
      },
      {
        "ordinal": 3,
        "name": "email",
        "type_info": "Varchar"
      },
      {
        "ordinal": 4,
        "name": "password_hash",
        "type_info": "Varchar"
      },
      {
        "ordinal": 5,
        "name": "registered_from_ip",
        "type_info": "Inet"
      },
      {
        "ordinal": 6,
        "name": "created_at",
        "type_info": "Timestamptz"
      },
      {
        "ordinal": 7,
        "name": "description",
        "type_info": "Text"
      },
      {
        "ordinal": 8,
        "name": "uploaded",
        "type_info": "Int8"
      },
      {
        "ordinal": 9,
        "name": "real_uploaded",
        "type_info": "Int8"
      },
      {
        "ordinal": 10,
        "name": "downloaded",
        "type_info": "Int8"
      },
      {
        "ordinal": 11,
        "name": "real_downloaded",
        "type_info": "Int8"
      },
      {
        "ordinal": 12,
        "name": "ratio",
        "type_info": "Float8"
      },
      {
        "ordinal": 13,
        "name": "required_ratio",
        "type_info": "Float8"
      },
      {
        "ordinal": 14,
        "name": "last_seen",
        "type_info": "Timestamptz"
      },
      {
        "ordinal": 15,
        "name": "class_name",
        "type_info": "Varchar"
      },
      {
        "ordinal": 16,
        "name": "class_locked",
        "type_info": "Bool"
      },
      {
        "ordinal": 17,
        "name": "permissions",
        "type_info": {
          "Custom": {
            "name": "user_permissions_enum[]",
            "kind": {
              "Array": {
                "Custom": {
                  "name": "user_permissions_enum",
                  "kind": {
                    "Enum": [
                      "create_user_class",
                      "edit_user_class",
                      "delete_user_class",
                      "edit_user_permissions",
                      "change_user_class",
                      "lock_user_class",
                      "upload_torrent",
                      "download_torrent",
                      "create_torrent_request",
                      "immune_activity_pruning",
                      "edit_title_group",
                      "edit_title_group_comment",
                      "edit_edition_group",
                      "edit_torrent",
                      "edit_artist",
                      "edit_collage",
                      "edit_series",
                      "edit_torrent_request",
                      "edit_forum_post",
                      "edit_forum_thread",
                      "edit_forum_sub_category",
                      "edit_forum_category",
                      "create_forum_category",
                      "create_forum_sub_category",
                      "create_forum_thread",
                      "create_forum_post",
                      "send_pm",
                      "create_css_sheet",
                      "edit_css_sheet",
                      "set_default_css_sheet",
                      "read_staff_pm",
                      "reply_staff_pm",
                      "resolve_staff_pm",
                      "unresolve_staff_pm",
                      "delete_title_group_tag",
                      "edit_title_group_tag",
                      "delete_torrent",
                      "get_user_application",
                      "update_user_application",
                      "warn_user",
                      "ban_user",
                      "edit_user",
                      "create_wiki_article",
                      "edit_wiki_article",
                      "edit_arcadia_settings",
                      "create_donation",
                      "edit_donation",
                      "delete_donation",
                      "search_donation"
                    ]
                  }
                }
              }
            }
          }
        }
      },
      {
        "ordinal": 18,
        "name": "forum_posts",
        "type_info": "Int4"
      },
      {
        "ordinal": 19,
        "name": "forum_threads",
        "type_info": "Int4"
      },
      {
        "ordinal": 20,
        "name": "torrent_comments",
        "type_info": "Int4"
      },
      {
        "ordinal": 21,
        "name": "request_comments",
        "type_info": "Int4"
      },
      {
        "ordinal": 22,
        "name": "artist_comments",
        "type_info": "Int8"
      },
      {
        "ordinal": 23,
        "name": "seeding",
        "type_info": "Int4"
      },
      {
        "ordinal": 24,
        "name": "leeching",
        "type_info": "Int4"
      },
      {
        "ordinal": 25,
        "name": "snatched",
        "type_info": "Int4"
      },
      {
        "ordinal": 26,
        "name": "seeding_size",
        "type_info": "Int8"
      },
      {
        "ordinal": 27,
        "name": "requests_filled",
        "type_info": "Int8"
      },
      {
        "ordinal": 28,
        "name": "collages_started",
        "type_info": "Int8"
      },
      {
        "ordinal": 29,
        "name": "requests_voted",
        "type_info": "Int8"
      },
      {
        "ordinal": 30,
        "name": "average_seeding_time",
        "type_info": "Int8"
      },
      {
        "ordinal": 31,
        "name": "invited",
        "type_info": "Int8"
      },
      {
        "ordinal": 32,
        "name": "invitations",
        "type_info": "Int2"
      },
      {
        "ordinal": 33,
        "name": "bonus_points",
        "type_info": "Int8"
      },
      {
        "ordinal": 34,
        "name": "freeleech_tokens",
        "type_info": "Int4"
      },
      {
        "ordinal": 35,
        "name": "passkey",
        "type_info": "Varchar"
      },
      {
        "ordinal": 36,
        "name": "warned",
        "type_info": "Bool"
      },
      {
        "ordinal": 37,
        "name": "banned",
        "type_info": "Bool"
      },
      {
        "ordinal": 38,
        "name": "staff_note",
        "type_info": "Text"
      },
      {
        "ordinal": 39,
        "name": "css_sheet_name",
        "type_info": "Varchar"
      }
    ],
    "parameters": {
      "Left": [
        "Text"
      ]
    },
    "nullable": [
      false,
      false,
      true,
      false,
      false,
      false,
      false,
      false,
      false,
      false,
      false,
      false,
      false,
      false,
      false,
      false,
      false,
      false,
      false,
      false,
      false,
      false,
      false,
      false,
      false,
      false,
      false,
      false,
      false,
      false,
      false,
      false,
      false,
      false,
      false,
      false,
      false,
      false,
      false,
      false
    ]
  },
  "hash": "4e362764b8f74fdced061ff73a3f59612e03035f1a9edaa33449602322fc9af6"
}
