{
  "db_name": "PostgreSQL",
  "query": "\n                    SELECT column_default\n                    FROM information_schema.columns\n                    WHERE table_name='users' AND column_name='css_sheet_name';\n                ",
  "describe": {
    "columns": [
      {
        "ordinal": 0,
        "name": "column_default",
        "type_info": "Varchar"
      }
    ],
    "parameters": {
      "Left": []
    },
    "nullable": [
      true
    ]
  },
  "hash": "68e3b62b9a7961d2145823f7980576bf90ffc9f09fcb8ae7e25d63627b8a9648"
}
