{
  "db_name": "PostgreSQL",
  "query": "\n            SELECT COUNT(*)::BIGINT\n            FROM torrent_requests tr\n            JOIN title_groups tg ON tr.title_group_id = tg.id\n            WHERE ($1::TEXT IS NULL OR tg.name ILIKE '%' || $1 || '%' OR $1 = ANY(tg.name_aliases))\n              AND ($2 OR tr.filled_at IS NULL)\n              AND ($3::INT IS NULL OR EXISTS (\n                  SELECT 1 FROM subscriptions_torrent_request_comments strc\n                  WHERE strc.torrent_request_id = tr.id AND strc.user_id = $3\n              ))\n            ",
  "describe": {
    "columns": [
      {
        "ordinal": 0,
        "name": "count",
        "type_info": "Int8"
      }
    ],
    "parameters": {
      "Left": [
        "Text",
        "Bool",
        "Int4"
      ]
    },
    "nullable": [
      null
    ]
  },
  "hash": "195c44ef34acff3f45d77471bc8ae5b16bc8b614bcbe5d21ac5893a78bc5dbf6"
}
